<?xml version="1.0" encoding="UTF-8" standalone="yes"?><ns2:GridDefinitionFileOutputV1 xmlns:ns2="http://www.gtech.com/xml/eInstants/base/common/CatAdminV1"><GridBody><GridProperties><Version>18</Version><GameType>0</GameType><GridSize>8000000</GridSize><RevFileSig>rStt7GbRleS3+W1Ii1U7YDqxU8+mzcCyj+35D9LrHeUdMJOHHNPQxIH7kyn2b9jMv45u39bJTBylxKFuSSb6uw==</RevFileSig><BigEndianFlg>false</BigEndianFlg><SiteID>62</SiteID><PricePoint>300</PricePoint><BetUnits>1</BetUnits><ValidationUnits>1</ValidationUnits><NoOfDivisions>19</NoOfDivisions><LongName>Tic Tac Toe Boost</LongName><ShortName>TT007</ShortName><GridMethod>0</GridMethod><GridTrigger>0</GridTrigger><GridTriggerUnit>0</GridTriggerUnit><VendorID>1</VendorID><IntAuditVendorID>2</IntAuditVendorID><ExtAuditVendorID>0</ExtAuditVendorID><DeliveryChannel>3</DeliveryChannel><Jackpot>false</Jackpot></GridProperties><DivisionRow><Winners>2</Winners><WinAmt>4000000</WinAmt><PrizeTableAmt>1000000</PrizeTableAmt><PrizeType>0</PrizeType></DivisionRow><DivisionRow><Winners>2</Winners><WinAmt>3000000</WinAmt><PrizeTableAmt>100000</PrizeTableAmt><PrizeType>0</PrizeType></DivisionRow><DivisionRow><Winners>2</Winners><WinAmt>2000000</WinAmt><PrizeTableAmt>50000</PrizeTableAmt><PrizeType>0</PrizeType></DivisionRow><DivisionRow><Winners>4</Winners><WinAmt>1000000</WinAmt><PrizeTableAmt>25000</PrizeTableAmt><PrizeType>0</PrizeType></DivisionRow><DivisionRow><Winners>10</Winners><WinAmt>400000</WinAmt><PrizeTableAmt>10000</PrizeTableAmt><PrizeType>0</PrizeType></DivisionRow><DivisionRow><Winners>20</Winners><WinAmt>200000</WinAmt><PrizeTableAmt>5000</PrizeTableAmt><PrizeType>0</PrizeType></DivisionRow><DivisionRow><Winners>90</Winners><WinAmt>100000</WinAmt><PrizeTableAmt>600</PrizeTableAmt><PrizeType>0</PrizeType></DivisionRow><DivisionRow><Winners>100</Winners><WinAmt>50000</WinAmt><PrizeTableAmt>300</PrizeTableAmt><PrizeType>0</PrizeType></DivisionRow><DivisionRow><Winners>150</Winners><WinAmt>25000</WinAmt><PrizeTableAmt>0</PrizeTableAmt><PrizeType>0</PrizeType></DivisionRow><DivisionRow><Winners>250</Winners><WinAmt>20000</WinAmt><PrizeTableAmt>0</PrizeTableAmt><PrizeType>0</PrizeType></DivisionRow><DivisionRow><Winners>750</Winners><WinAmt>15000</WinAmt><PrizeTableAmt>0</PrizeTableAmt><PrizeType>0</PrizeType></DivisionRow><DivisionRow><Winners>1000</Winners><WinAmt>10000</WinAmt><PrizeTableAmt>0</PrizeTableAmt><PrizeType>0</PrizeType></DivisionRow><DivisionRow><Winners>15000</Winners><WinAmt>5000</WinAmt><PrizeTableAmt>0</PrizeTableAmt><PrizeType>0</PrizeType></DivisionRow><DivisionRow><Winners>25000</Winners><WinAmt>2400</WinAmt><PrizeTableAmt>0</PrizeTableAmt><PrizeType>0</PrizeType></DivisionRow><DivisionRow><Winners>50000</Winners><WinAmt>1800</WinAmt><PrizeTableAmt>0</PrizeTableAmt><PrizeType>0</PrizeType></DivisionRow><DivisionRow><Winners>250000</Winners><WinAmt>1200</WinAmt><PrizeTableAmt>0</PrizeTableAmt><PrizeType>0</PrizeType></DivisionRow><DivisionRow><Winners>881750</Winners><WinAmt>600</WinAmt><PrizeTableAmt>0</PrizeTableAmt><PrizeType>0</PrizeType></DivisionRow><DivisionRow><Winners>1600000</Winners><WinAmt>300</WinAmt><PrizeTableAmt>0</PrizeTableAmt><PrizeType>0</PrizeType></DivisionRow><DivisionRow><Winners>5175870</Winners><WinAmt>0</WinAmt><PrizeTableAmt>0</PrizeTableAmt><PrizeType>0</PrizeType></DivisionRow></GridBody><GridFooter><checksum enc="hex">B07094216E396F2340EB3AF1FDB1E2DBD8FCAB6E02E6F2F783074DCB721FFD31</checksum></GridFooter></ns2:GridDefinitionFileOutputV1>